[
    {
      "id": 1,
      "image": "https://www.praavahealth.com/media-images/l_yeyk2Sd_-PkwUYYAksaewIXck=/51/fill-500x666-c0/Taslima.png",
      "name": "Dr. Ayesha Rahman",
      "education": "MBBS, FCPS",
      "speciality": "Medicine",
      "experience": "10 years",
      "registrationNumber": "BMDC123456",
      "detailsRoute": "/doctors/1",
      "hospital": "TMSS Medical College & Rafatullah Community Hospital, Bogura",
      "availability": ["Sunday", "Monday", "Thursday"],
      "fee": 400,
      "feeNote": "(incl. Vat)",
      "feeLabel": "Per consultation"
    },
    {
      "id": 2,
      "image": "https://doctorslist.info/wp-content/uploads/2022/08/10-Best-Doctors-in-Bangladesh-1.png",
      "name": "Dr. Farhan Ahmed",
      "education": "MBBS, MS",
      "speciality": "Orthopedic Surgeon",
      "experience": "8 years",
      "registrationNumber": "BMDC654321",
      "detailsRoute": "/doctors/2",
      "hospital": "Dhaka Medical College Hospital",
      "regNo": "BD 654321",
      "availability": ["Monday", "Tuesday", "Wednesday"],
      "fee": 500,
      "feeNote": "(incl. Vat)",
      "feeLabel": "Per consultation"
    },
    {
      "id": 3,
      "image": "https://encrypted-tbn0.gstatic.com/images?q=tbn:ANd9GcTRekct7GsZdBua3TPdpkj14B6ZAmuAcDdULzD8csB1gHeDz9NNoYrh5dnsr8p4ZFdwbHw&usqp=CAU",
      "name": "Dr. Nusrat Jahan",
      "education": "MBBS, MD",
      "speciality": "Cardiologist",
      "experience": "12 years",
      "registrationNumber": "BMDC112233",
      "detailsRoute": "/doctors/3",
      "hospital": "National Heart Foundation, Dhaka",
      "regNo": "BD 112233",
      "availability": ["Sunday", "Tuesday", "Friday"],
      "fee": 800,
      "feeNote": "(incl. Vat)",
      "feeLabel": "Per consultation"
    },
    {
      "id": 4,
      "image": "https://umchltd.com/assets/images/doctor/15d734248c07c5ab14d470da2cc5b700.jpg",
      "name": "Dr. Imran Kabir",
      "education": "MBBS, FCPS",
      "speciality": "General Surgeon",
      "experience": "15 years",
      "registrationNumber": "BMDC445566",
      "detailsRoute": "/doctors/4",
      "hospital": "United Hospital, Dhaka",
      "regNo": "BD 445566",
      "availability": ["Saturday", "Monday", "Thursday"],
      "fee": 500,
      "feeNote": "(incl. Vat)",
      "feeLabel": "Per consultation"
    },
    {
      "id": 5,
      "image": "https://yt3.googleusercontent.com/OKQaRdItmuFRKIDooobVVX7xJgaSLbsbr0-MRbFps-bONQ1QEQp6Tm1eyYC5GHra4_AuQNhz=s900-c-k-c0x00ffffff-no-rj",
      "name": "Dr. Tasnim Jara",
      "education": "MBBS, DGO",
      "speciality": "Gynecologist",
      "experience": "9 years",
      "registrationNumber": "BMDC778899",
      "detailsRoute": "/doctors/5",
      "hospital": "Ibrahim Cardiac Hospital & Research Institute",
      "regNo": "BD 778899",
      "availability": ["Sunday", "Wednesday", "Thursday"],
      "fee": 400,
      "feeNote": "(incl. Vat)",
      "feeLabel": "Per consultation"
    },
    {
      "id": 6,
      "image": "https://mmchospital.in/storage/doctors/thumbs/VMME5D0ZucPdEsXqz1216e1sx4LKZgB2mt9f1GNH.png",
      "name": "Dr. Tahmid Hossain",
      "education": "MBBS, MD",
      "speciality": "Dermatologist",
      "experience": "7 years",
      "registrationNumber": "BMDC998877",
      "detailsRoute": "/doctors/6",
      "hospital": "Popular Diagnostic Center, Dhanmondi",
      "regNo": "BD 998877",
      "availability": ["Monday", "Thursday", "Friday"],
      "fee": 320,
      "feeNote": "(incl. Vat)",
      "feeLabel": "Per consultation"
    },
    {
      "id": 7,
      "image": "https://encrypted-tbn0.gstatic.com/images?q=tbn:ANd9GcSw4LoTcEYIiXtm_3qEyAfUsCHoO-YxQxcs-swIbGgO0o_XajgEvEWzgEgLpdoaGlfVD8Q&usqp=CAU",
      "name": "Dr. Saima Chowdhury",
      "education": "MBBS, FCPS",
      "speciality": "Pediatrician",
      "experience": "11 years",
      "registrationNumber": "BMDC665544",
      "detailsRoute": "/doctors/7",
      "hospital": "Square Hospitals Ltd.",
      "regNo": "BD 665544",
      "availability": ["Sunday", "Tuesday", "Wednesday"],
      "fee": 330,
      "feeNote": "(incl. Vat)",
      "feeLabel": "Per consultation"
    },
    {
      "id": 8,
      "image": "https://encrypted-tbn0.gstatic.com/images?q=tbn:ANd9GcTcyDSvEtqZ3Qqm-xD0jNnmAhmWh6P8erJ29b0IZo0ow-bEJtE8WqSr6OLPcyBcplBC2dQ&usqp=CAU",
      "name": "Dr. Anwar Hossain",
      "education": "MBBS, MS",
      "speciality": "ENT Specialist",
      "experience": "13 years",
      "registrationNumber": "BMDC443322",
      "detailsRoute": "/doctors/8",
      "hospital": "Green Life Medical College Hospital",
      "regNo": "BD 443322",
      "availability": ["Saturday", "Monday", "Wednesday"],
      "fee": 550,
      "feeNote": "(incl. Vat)",
      "feeLabel": "Per consultation"
    },
    {
      "id": 9,
      "image": "https://www.squarehospital.com/storage/images/1521006196Dr_Bidora_(4).JPG",
      "name": "Dr. Munira Sultana",
      "education": "MBBS, MD",
      "speciality": "Neurologist",
      "experience": "10 years",
      "registrationNumber": "BMDC221100",
      "detailsRoute": "/doctors/9",
      "hospital": "Square Hospitals Ltd.",
      "regNo": "BD 221100",
      "availability": ["Tuesday", "Thursday", "Saturday"],
      "fee": 1500,
      "feeNote": "(incl. Vat)",
      "feeLabel": "Per consultation"
    },
    {
      "id": 10,
      "image": "https://encrypted-tbn0.gstatic.com/images?q=tbn:ANd9GcTClFGLYV9--z_pWC9IDXtvp-5out7vhlHa3hY4iHFkj_ts4C8GizmvU-9I3tMWc9i0s5w&usqp=CAU",
      "name": "Dr. Tareq Mahmood",
      "education": "MBBS, FCPS",
      "speciality": "Urologist",
      "experience": "6 years",
      "registrationNumber": "BMDC334455",
      "detailsRoute": "/doctors/10",
      "hospital": "Bangabandhu Sheikh Mujib Medical University (BSMMU)",
      "regNo": "BD 334455",
      "availability": ["Sunday", "Monday", "Wednesday"],
      "fee": 650,
      "feeNote": "(incl. Vat)",
      "feeLabel": "Per consultation"
    },
    {
      "id": 11,
      "image": "https://mail.daktarbook.com/uploaded/doctor/1674029141_63c7a855d202b.jpg",
      "name": "Dr. Lubna Naznin",
      "education": "MBBS, MD",
      "speciality": "Psychiatrist",
      "experience": "5 years",
      "registrationNumber": "BMDC667788",
      "detailsRoute": "/doctors/11",
      "hospital": "National Institute of Mental Health, Dhaka",
      "regNo": "BD 667788",
      "availability": ["Tuesday", "Thursday", "Friday"],
      "fee": 1000,
      "feeNote": "(incl. Vat)",
      "feeLabel": "Per consultation"
    },
    {
      "id": 12,
      "image": "https://www.kimshealth.org/media/filer_public_thumbnails/filer_public/99/1e/991e4289-8d8d-49a9-8023-26acbb4331fe/dr_derin_d1.jpg__253x285_q85_crop_subsampling-2.jpg",
      "name": "Dr. Shahin Alam",
      "education": "MBBS, FCPS",
      "speciality": "Anesthesiologist",
      "experience": "14 years",
      "registrationNumber": "BMDC990011",
      "detailsRoute": "/doctors/12",
      "hospital": "Ibn Sina Specialized Hospital",
      "regNo": "BD 990011",
      "availability": ["Saturday", "Sunday", "Monday"],
      "fee": 750,
      "feeNote": "(incl. Vat)",
      "feeLabel": "Per consultation"
    }
  ]
